[
  "{\n  \"topics\": [\n    {\n      \"name\": \"Hackathon Setup Guide\",\n      \"description\": \"This guide provides a step-by-step process for setting up Featherless.ai, an AI inference platform, and integrating it into your projects.\",\n      \"keywords\": [\"Featherless.ai\", \"Hackathon\", \"AI Inference\"],\n      \"context\": [\"serverless AI\", \"unlimited access\", \"open-source AI models\"]\n    }\n  ],\n  \"summary\": \"The guide covers setting up Featherless.ai, including signing up, obtaining an API key, choosing a model, and making your first API call. It also provides troubleshooting tips and links to additional resources.\"\n}"
]